{"data_mtime":1731412598,"dep_lines":[1,1,1,1,1,1,1],"dep_prios":[5,30,30,30,30,30,30],"dependencies":["builtins","_collections_abc","_typeshed","abc","importlib","importlib.machinery","typing"],"hash":"50dc0159b3e057b4c3f983e6cb3473bbdc6345321e9378eb2938f98cc557bdec","id":"03_in_stock","ignore_all":false,"interface_hash":"0f73a5c5b8d26fcb50d9b144f6d2ab3dc00af38e7c47bd32e7d5d2554093ba4d","mtime":1731412860,"options":{"allow_redefinition":false,"allow_untyped_globals":false,"always_false":[],"always_true":[],"bazel":false,"check_untyped_defs":false,"disable_bytearray_promotion":false,"disable_error_code":[],"disable_memoryview_promotion":false,"disabled_error_codes":[],"disallow_any_decorated":false,"disallow_any_explicit":false,"disallow_any_expr":false,"disallow_any_generics":false,"disallow_any_unimported":false,"disallow_incomplete_defs":false,"disallow_subclassing_any":false,"disallow_untyped_calls":false,"disallow_untyped_decorators":false,"disallow_untyped_defs":false,"enable_error_code":[],"enabled_error_codes":[],"extra_checks":false,"follow_imports":"normal","follow_imports_for_stubs":false,"ignore_errors":false,"ignore_missing_imports":false,"implicit_optional":false,"implicit_reexport":true,"local_partial_types":false,"mypyc":false,"old_type_inference":false,"platform":"win32","plugins":[],"strict_concatenate":false,"strict_equality":false,"strict_optional":true,"warn_no_return":true,"warn_return_any":false,"warn_unreachable":false,"warn_unused_ignores":false},"path":"p:\\Assiginment_Piaic\\53_self_coding_challenges_07_information_flow\\03_in_stock.py","plugin_data":null,"size":617,"suppressed":[],"version_id":"1.11.2"}